bond_order_processing/__init__.py
bond_order_processing/calculations.py
bond_order_processing/calculations_for_atoms_lists.py
bond_order_processing/input_data.py
bond_order_processing-1.1.2.dist-info/LICENSE.txt
bond_order_processing-1.1.2.dist-info/METADATA
bond_order_processing-1.1.2.dist-info/WHEEL
bond_order_processing-1.1.2.dist-info/top_level.txt
bond_order_processing-1.1.2.dist-info/RECORD
