Metadata-Version: 2.1
Name: bond-order-processing
Version: 1.1.2
Summary: Process Mayer bond orders from ab inito calculations.
Author-email: Paweł Goj <pawel.goj5@gmail.com>
Keywords: packaging,dependency,infer,pyproject.toml
Classifier: License :: OSI Approved :: MIT License
Classifier: Natural Language :: English
Classifier: Operating System :: OS Independent
Classifier: Programming Language :: Python
Requires-Python: >=3.10
License-File: LICENSE.txt
Requires-Dist: attrs (==22.2.0)
Requires-Dist: autopep8 (>=2.0.0)
Requires-Dist: certifi (==2022.9.24)
Requires-Dist: charset-normalizer (==2.1.1)
Requires-Dist: click (==8.1.3)
Requires-Dist: colorama (==0.4.6)
Requires-Dist: docutils (==0.19)
Requires-Dist: exceptiongroup (==1.1.0)
Requires-Dist: numpy (==1.24.1)
Requires-Dist: PyYAML (==6.0)
